smulib/__init__.py
smulib/smu/__init__.py
smulib/smu/base.py
smulib/smu/smu.py
smulib-0.0.2.dist-info/METADATA
smulib-0.0.2.dist-info/WHEEL
smulib-0.0.2.dist-info/RECORD
