Metadata-Version: 2.4
Name: smulib
Version: 0.0.2
Summary: SMU Library
Project-URL: Homepage, https://github.com/pypa/sampleproject
Project-URL: Issues, https://github.com/pypa/sampleproject/issues
Author-email: Guus Kamphuis <guuskamphuis@gmail.com>
License-Expression: MIT
Classifier: Operating System :: OS Independent
Classifier: Programming Language :: Python :: 3
Requires-Python: >=3.12
